wx_icons_tango/__init__.py
wx_icons_tango/py.typed
wx_icons_tango/Tango/__init__.py
wx_icons_tango/Tango/index.theme
wx_icons_tango/Tango/16x16/actions/address-book-new.png
wx_icons_tango/Tango/16x16/actions/appointment-new.png
wx_icons_tango/Tango/16x16/actions/bookmark-new.png
wx_icons_tango/Tango/16x16/actions/contact-new.png
wx_icons_tango/Tango/16x16/actions/document-new.png
wx_icons_tango/Tango/16x16/actions/document-open.png
wx_icons_tango/Tango/16x16/actions/document-print-preview.png
wx_icons_tango/Tango/16x16/actions/document-print.png
wx_icons_tango/Tango/16x16/actions/document-properties.png
wx_icons_tango/Tango/16x16/actions/document-save-as.png
wx_icons_tango/Tango/16x16/actions/document-save.png
wx_icons_tango/Tango/16x16/actions/edit-clear.png
wx_icons_tango/Tango/16x16/actions/edit-copy.png
wx_icons_tango/Tango/16x16/actions/edit-cut.png
wx_icons_tango/Tango/16x16/actions/edit-delete.png
wx_icons_tango/Tango/16x16/actions/edit-find-replace.png
wx_icons_tango/Tango/16x16/actions/edit-find.png
wx_icons_tango/Tango/16x16/actions/edit-paste.png
wx_icons_tango/Tango/16x16/actions/edit-redo.png
wx_icons_tango/Tango/16x16/actions/edit-select-all.png
wx_icons_tango/Tango/16x16/actions/edit-undo.png
wx_icons_tango/Tango/16x16/actions/folder-new.png
wx_icons_tango/Tango/16x16/actions/format-indent-less.png
wx_icons_tango/Tango/16x16/actions/format-indent-more.png
wx_icons_tango/Tango/16x16/actions/format-justify-center.png
wx_icons_tango/Tango/16x16/actions/format-justify-fill.png
wx_icons_tango/Tango/16x16/actions/format-justify-left.png
wx_icons_tango/Tango/16x16/actions/format-justify-right.png
wx_icons_tango/Tango/16x16/actions/format-text-bold.png
wx_icons_tango/Tango/16x16/actions/format-text-italic.png
wx_icons_tango/Tango/16x16/actions/format-text-strikethrough.png
wx_icons_tango/Tango/16x16/actions/format-text-underline.png
wx_icons_tango/Tango/16x16/actions/go-bottom.png
wx_icons_tango/Tango/16x16/actions/go-down.png
wx_icons_tango-0.2.0.dist-info/AUTHORS
wx_icons_tango-0.2.0.dist-info/LICENSE
wx_icons_tango-0.2.0.dist-info/METADATA
wx_icons_tango-0.2.0.dist-info/WHEEL
wx_icons_tango-0.2.0.dist-info/top_level.txt
wx_icons_tango-0.2.0.dist-info/RECORD
