Metadata-Version: 2.1
Name: wx-icons-tango
Version: 0.2.0
Summary: Tango icon theme for wxPython 🐍
Home-page: https://github.com/domdfcoding/custom_wx_icons_tango
Author: Dominic Davis-Foster
Author-email: Dominic Davis-Foster <dominic@davis-foster.co.uk>
License: GNU LESSER GENERAL PUBLIC LICENSE
Project-URL: Homepage, https://github.com/domdfcoding/custom_wx_icons_tango
Project-URL: Issue Tracker, https://github.com/domdfcoding/custom_wx_icons_tango/issues
Project-URL: Source Code, https://github.com/domdfcoding/custom_wx_icons_tango
Project-URL: Documentation, https://custom-wx-icons-tango.readthedocs.io/en/latest
Keywords: icons,iconset,tango,wxpython
Platform: Windows
Platform: macOS
Platform: Linux
Classifier: Development Status :: 3 - Alpha
Classifier: Environment :: X11 Applications :: GTK
Classifier: Intended Audience :: Developers
Classifier: License :: OSI Approved :: GNU Lesser General Public License v3 or later (LGPLv3+)
Classifier: Operating System :: OS Independent
Classifier: Operating System :: POSIX :: Linux
Classifier: Programming Language :: Python
Classifier: Programming Language :: Python :: 3 :: Only
Classifier: Programming Language :: Python :: 3.7
Classifier: Programming Language :: Python :: 3.8
Classifier: Programming Language :: Python :: 3.9
Classifier: Programming Language :: Python :: 3.10
Classifier: Programming Language :: Python :: 3.11
Classifier: Programming Language :: Python :: 3.12
Classifier: Programming Language :: Python :: 3.13
Classifier: Programming Language :: Python :: Implementation :: CPython
Classifier: Topic :: Desktop Environment :: Gnome
Classifier: Topic :: Software Development :: Libraries :: Python Modules
Classifier: Topic :: Software Development :: User Interfaces
Classifier: Typing :: Typed
Requires-Python: >=3.7
License-File: LICENSE
License-File: AUTHORS
Requires-Dist: domdf-python-tools>=3.8.0.post
Requires-Dist: wx-icons-hicolor>=0.1.4
Requires-Dist: wxpython>=4.0.7; platform_system == "Darwin" and python_version < "3.9"
Requires-Dist: wxpython>=4.0.7; platform_system == "Windows" and python_version < "3.9"
